MANIFEST.in
NEWS.txt
README.rst
setup.py
bin/cnv2nc
bin/cnvdump
src/cnv/__init__.py
src/cnv/checks.py
src/cnv/cnv.py
src/cnv/netcdf.py
src/cnv.egg-info/PKG-INFO
src/cnv.egg-info/SOURCES.txt
src/cnv.egg-info/dependency_links.txt
src/cnv.egg-info/entry_points.txt
src/cnv.egg-info/not-zip-safe
src/cnv.egg-info/requires.txt
src/cnv.egg-info/top_level.txt
src/cnv/rules/binary.yaml
src/cnv/rules/cnv.yaml
src/cnv/rules/cnv2.yaml
src/cnv/rules/refnames.yaml
src/cnv/rules/teste