Metadata-Version: 1.1
Name: cnv
Version: 0.3.2
Summary: Parser for .cnv files, the Sea-Bird CTD data format.
Home-page: http://pycnv.castelao.net
Author: Guilherme Castelao , Luiz Irber
Author-email: guilherme@castelao.net, luiz.irber@gmail.com
License: PSF
Download-URL: http://pypi.python.org/packages/source/c/cnv/cnv-0.3.2.tar.gz
Keywords: parser oceanography data CTD SeaBird
Platform: any
Classifier: Development Status :: 4 - Beta
Classifier: Intended Audience :: Science/Research
Classifier: License :: OSI Approved :: Python Software Foundation License
Classifier: Operating System :: OS Independent
Classifier: Programming Language :: Python
Classifier: Programming Language :: Python :: 2
Classifier: Topic :: Scientific/Engineering
